termdoro/main.py
termdoro/termdoro.mp3
termdoro/termdoro.png
termdoro-2.0.0.dist-info/LICENSE
termdoro-2.0.0.dist-info/METADATA
termdoro-2.0.0.dist-info/WHEEL
termdoro-2.0.0.dist-info/entry_points.txt
termdoro-2.0.0.dist-info/top_level.txt
termdoro-2.0.0.dist-info/RECORD
