Metadata-Version: 2.1
Name: termdoro
Version: 2.0.0
Summary: Pomodoro in your terminal
Home-page: https://github.com/niyazisuleymanov/termdoro
Author: Niyazi Suleymanov
Author-email: niyazisuleymanov@protonmail.com
License: MIT
Project-URL: Bug Tracker, https://github.com/niyazisuleymanov/termdoro/issues
Classifier: Programming Language :: Python :: 3
Classifier: License :: OSI Approved :: MIT License
Classifier: Operating System :: OS Independent
Requires-Python: >=3.6
License-File: LICENSE
Requires-Dist: bullet
Requires-Dist: python-dateutil
Requires-Dist: playsound
Requires-Dist: pyfiglet
